CeleryStalk/__init__.py
CeleryStalk/parallelised_pandas_apply.py
CeleryStalk/paralleliser.py
CeleryStalk/paralleliser_bk.py
CeleryStalk/test.py
CeleryStalk-1.3.6.dist-info/LICENSE.txt
CeleryStalk-1.3.6.dist-info/METADATA
CeleryStalk-1.3.6.dist-info/WHEEL
CeleryStalk-1.3.6.dist-info/top_level.txt
CeleryStalk-1.3.6.dist-info/RECORD
