Metadata-Version: 2.1
Name: CeleryStalk
Version: 1.3.6
Summary: Change Large CSVs Faster with Easy Parallel Processing
Home-page: http://pypi.python.org/pypi/CeleryStalk/
Author: Rudy Venguswamy
Author-email: rvenguswamy@vmware.com
License: LICENSE.txt
Platform: UNKNOWN
Requires-Dist: celery (>=4.2.0)
Requires-Dist: redis (>=2.10.5)
